jps_api_wrapper/__init__.py
jps_api_wrapper/classic.py
jps_api_wrapper/pro.py
jps_api_wrapper/request_builder.py
jps_api_wrapper/utils.py
jps_api_wrapper-1.17.0.dist-info/LICENSE
jps_api_wrapper-1.17.0.dist-info/METADATA
jps_api_wrapper-1.17.0.dist-info/WHEEL
jps_api_wrapper-1.17.0.dist-info/top_level.txt
jps_api_wrapper-1.17.0.dist-info/RECORD
