Metadata-Version: 2.1
Name: jps_api_wrapper
Version: 1.17.0
Summary: Jamf Pro Server API Python wrapper
License: MIT
Classifier: License :: OSI Approved :: MIT License
Classifier: Development Status :: 5 - Production/Stable
Classifier: Intended Audience :: Developers
Classifier: Topic :: Software Development :: Libraries
Requires-Python: >=3.6
License-File: LICENSE
Requires-Dist: jamf-api-auth
Requires-Dist: requests
